MANIFEST.in
README.rst
setup.cfg
setup.py
vucli/__init__.py
vucli/vucli.py
vucli.egg-info/PKG-INFO
vucli.egg-info/SOURCES.txt
vucli.egg-info/dependency_links.txt
vucli.egg-info/entry_points.txt
vucli.egg-info/requires.txt
vucli.egg-info/top_level.txt