Metadata-Version: 1.0
Name: vucli
Version: 0.0.3
Summary: Vultr VPS cloud CLI console
Home-page: https://github.com/yikaus/vultrcli
Author: Kevin Yi
Author-email: UNKNOWN
License: BSD
Keywords: cloud CLI REST admin administrator node vultr
Platform: UNKNOWN
